django_quizblock_random-0.2.0.dist-info/DESCRIPTION.rst
django_quizblock_random-0.2.0.dist-info/METADATA
django_quizblock_random-0.2.0.dist-info/RECORD
django_quizblock_random-0.2.0.dist-info/WHEEL
django_quizblock_random-0.2.0.dist-info/metadata.json
django_quizblock_random-0.2.0.dist-info/top_level.txt
quizblock_random/__init__.py
quizblock_random/__init__.pyc
quizblock_random/admin.py
quizblock_random/admin.pyc
quizblock_random/exportimport.py
quizblock_random/models.py
quizblock_random/models.pyc
quizblock_random/urls.py
quizblock_random/urls.pyc
quizblock_random/views.py
quizblock_random/views.pyc
quizblock_random/migrations/0001_initial.py
quizblock_random/migrations/0001_initial.pyc
quizblock_random/migrations/__init__.py
quizblock_random/migrations/__init__.pyc
quizblock_random/static/quizblock_random/css/quizblock_random.css
quizblock_random/static/quizblock_random/js/quizblock_random.js
quizblock_random/templates/quizblock_random/answer_confirm_delete.html
quizblock_random/templates/quizblock_random/complete_quiz_feedback.html
quizblock_random/templates/quizblock_random/edit_answer.html
quizblock_random/templates/quizblock_random/edit_question.html
quizblock_random/templates/quizblock_random/long_answer_show_answer.html
quizblock_random/templates/quizblock_random/long_text.html
quizblock_random/templates/quizblock_random/multiple_choice.html
quizblock_random/templates/quizblock_random/multiple_choice_show_answer.html
quizblock_random/templates/quizblock_random/question.html
quizblock_random/templates/quizblock_random/question_confirm_delete.html
quizblock_random/templates/quizblock_random/quizblock_random.html
quizblock_random/templates/quizblock_random/quizrandom_detail.html
quizblock_random/templates/quizblock_random/short_text.html
quizblock_random/templates/quizblock_random/show_answer.html
quizblock_random/templates/quizblock_random/single_choice.html
quizblock_random/templates/quizblock_random/single_choice_completed.html
quizblock_random/templates/quizblock_random/single_choice_dropdown.html
quizblock_random/templates/quizblock_random/single_choice_show_answer.html
quizblock_random/templatetags/__init__.py
quizblock_random/templatetags/__init__.pyc
quizblock_random/templatetags/getquestionuserlock.py
