Metadata-Version: 2.0
Name: django-quizblock-random
Version: 0.2.0
Summary: Random Quiz PageBlock
Home-page: https://github.com/ccnmtl/django-quizblock-random
Author: James Davis
Author-email: jed.davis13@gmail.com
License: BSD
Platform: any
Requires-Dist: django-pagetree (>=1.1.2)
Requires-Dist: django-quizblock (>=1.1.3)
